<?xml version="1.0"?>
<annotation>
    <filename>000001153.jpg</filename>
    <source>
        <annotation>ArcGIS Pro 2.1</annotation>
    </source>
    <size>
        <width>224</width>
        <height>224</height>
        <depth>3</depth>
    </size>
    <object>
        <name>1</name>
        <bndbox>
            <xmin>96.06</xmin>
            <ymin>0.00</ymin>
            <xmax>105.67</xmax>
            <ymax>2.77</ymax>
        </bndbox>
    </object>
    <object>
        <name>1</name>
        <bndbox>
            <xmin>75.64</xmin>
            <ymin>18.08</ymin>
            <xmax>86.75</xmax>
            <ymax>29.19</ymax>
        </bndbox>
    </object>
    <object>
        <name>1</name>
        <bndbox>
            <xmin>108.22</xmin>
            <ymin>18.08</ymin>
            <xmax>119.34</xmax>
            <ymax>29.19</ymax>
        </bndbox>
    </object>
    <object>
        <name>1</name>
        <bndbox>
            <xmin>131.12</xmin>
            <ymin>49.19</ymin>
            <xmax>142.23</xmax>
            <ymax>60.30</ymax>
        </bndbox>
    </object>
    <object>
        <name>1</name>
        <bndbox>
            <xmin>186.89</xmin>
            <ymin>117.58</ymin>
            <xmax>198.00</xmax>
            <ymax>128.70</ymax>
        </bndbox>
    </object>
</annotation>
