<?xml version="1.0"?>
<annotation>
    <filename>000001695.jpg</filename>
    <source>
        <annotation>ArcGIS Pro 2.1</annotation>
    </source>
    <size>
        <width>224</width>
        <height>224</height>
        <depth>3</depth>
    </size>
    <object>
        <name>2</name>
        <bndbox>
            <xmin>169.80</xmin>
            <ymin>79.65</ymin>
            <xmax>214.24</xmax>
            <ymax>124.09</ymax>
        </bndbox>
    </object>
    <object>
        <name>2</name>
        <bndbox>
            <xmin>65.99</xmin>
            <ymin>103.29</ymin>
            <xmax>110.43</xmax>
            <ymax>147.73</ymax>
        </bndbox>
    </object>
    <object>
        <name>2</name>
        <bndbox>
            <xmin>74.21</xmin>
            <ymin>192.96</ymin>
            <xmax>118.65</xmax>
            <ymax>224.00</ymax>
        </bndbox>
    </object>
    <object>
        <name>2</name>
        <bndbox>
            <xmin>147.96</xmin>
            <ymin>149.02</ymin>
            <xmax>192.40</xmax>
            <ymax>193.47</ymax>
        </bndbox>
    </object>
    <object>
        <name>1</name>
        <bndbox>
            <xmin>0.10</xmin>
            <ymin>37.78</ymin>
            <xmax>11.21</xmax>
            <ymax>48.89</ymax>
        </bndbox>
    </object>
</annotation>
