<?xml version="1.0"?>
<annotation>
    <filename>000000348.jpg</filename>
    <source>
        <annotation>ArcGIS Pro 2.1</annotation>
    </source>
    <size>
        <width>224</width>
        <height>224</height>
        <depth>3</depth>
    </size>
    <object>
        <name>2</name>
        <bndbox>
            <xmin>165.97</xmin>
            <ymin>199.06</ymin>
            <xmax>210.41</xmax>
            <ymax>224.00</ymax>
        </bndbox>
    </object>
    <object>
        <name>1</name>
        <bndbox>
            <xmin>137.50</xmin>
            <ymin>0.00</ymin>
            <xmax>148.48</xmax>
            <ymax>4.72</ymax>
        </bndbox>
    </object>
    <object>
        <name>1</name>
        <bndbox>
            <xmin>198.93</xmin>
            <ymin>11.18</ymin>
            <xmax>210.04</xmax>
            <ymax>22.29</ymax>
        </bndbox>
    </object>
    <object>
        <name>1</name>
        <bndbox>
            <xmin>157.71</xmin>
            <ymin>86.87</ymin>
            <xmax>168.82</xmax>
            <ymax>97.98</ymax>
        </bndbox>
    </object>
    <object>
        <name>1</name>
        <bndbox>
            <xmin>55.66</xmin>
            <ymin>107.14</ymin>
            <xmax>66.78</xmax>
            <ymax>118.25</ymax>
        </bndbox>
    </object>
    <object>
        <name>1</name>
        <bndbox>
            <xmin>71.21</xmin>
            <ymin>183.84</ymin>
            <xmax>82.32</xmax>
            <ymax>194.96</ymax>
        </bndbox>
    </object>
    <object>
        <name>1</name>
        <bndbox>
            <xmin>85.06</xmin>
            <ymin>182.49</ymin>
            <xmax>96.17</xmax>
            <ymax>193.60</ymax>
        </bndbox>
    </object>
    <object>
        <name>1</name>
        <bndbox>
            <xmin>186.09</xmin>
            <ymin>69.98</ymin>
            <xmax>197.20</xmax>
            <ymax>81.09</ymax>
        </bndbox>
    </object>
    <object>
        <name>1</name>
        <bndbox>
            <xmin>98.52</xmin>
            <ymin>84.15</ymin>
            <xmax>109.63</xmax>
            <ymax>95.26</ymax>
        </bndbox>
    </object>
</annotation>
