<?xml version="1.0"?>
<annotation>
    <filename>000000928.jpg</filename>
    <source>
        <annotation>ArcGIS Pro 2.1</annotation>
    </source>
    <size>
        <width>224</width>
        <height>224</height>
        <depth>3</depth>
    </size>
    <object>
        <name>2</name>
        <bndbox>
            <xmin>128.10</xmin>
            <ymin>207.28</ymin>
            <xmax>171.15</xmax>
            <ymax>224.00</ymax>
        </bndbox>
    </object>
    <object>
        <name>1</name>
        <bndbox>
            <xmin>36.33</xmin>
            <ymin>1.44</ymin>
            <xmax>47.44</xmax>
            <ymax>12.56</ymax>
        </bndbox>
    </object>
</annotation>
