<?xml version="1.0"?>
<annotation>
    <filename>000003584.jpg</filename>
    <source>
        <annotation>ArcGIS Pro 2.1</annotation>
    </source>
    <size>
        <width>224</width>
        <height>224</height>
        <depth>3</depth>
    </size>
    <object>
        <name>1</name>
        <bndbox>
            <xmin>30.66</xmin>
            <ymin>95.14</ymin>
            <xmax>41.78</xmax>
            <ymax>106.25</ymax>
        </bndbox>
    </object>
    <object>
        <name>1</name>
        <bndbox>
            <xmin>56.61</xmin>
            <ymin>115.49</ymin>
            <xmax>67.72</xmax>
            <ymax>126.60</ymax>
        </bndbox>
    </object>
    <object>
        <name>1</name>
        <bndbox>
            <xmin>77.04</xmin>
            <ymin>130.84</ymin>
            <xmax>88.15</xmax>
            <ymax>141.95</ymax>
        </bndbox>
    </object>
    <object>
        <name>1</name>
        <bndbox>
            <xmin>99.53</xmin>
            <ymin>149.97</ymin>
            <xmax>110.64</xmax>
            <ymax>161.09</ymax>
        </bndbox>
    </object>
</annotation>
