<?xml version="1.0"?>
<annotation>
    <filename>000003139.jpg</filename>
    <source>
        <annotation>ArcGIS Pro 2.1</annotation>
    </source>
    <size>
        <width>224</width>
        <height>224</height>
        <depth>3</depth>
    </size>
    <object>
        <name>2</name>
        <bndbox>
            <xmin>1.45</xmin>
            <ymin>170.78</ymin>
            <xmax>45.89</xmax>
            <ymax>215.23</ymax>
        </bndbox>
    </object>
    <object>
        <name>1</name>
        <bndbox>
            <xmin>0.00</xmin>
            <ymin>32.57</ymin>
            <xmax>3.09</xmax>
            <ymax>42.52</ymax>
        </bndbox>
    </object>
    <object>
        <name>1</name>
        <bndbox>
            <xmin>26.87</xmin>
            <ymin>33.94</ymin>
            <xmax>37.99</xmax>
            <ymax>45.05</ymax>
        </bndbox>
    </object>
    <object>
        <name>1</name>
        <bndbox>
            <xmin>136.42</xmin>
            <ymin>187.19</ymin>
            <xmax>147.53</xmax>
            <ymax>198.30</ymax>
        </bndbox>
    </object>
    <object>
        <name>1</name>
        <bndbox>
            <xmin>190.71</xmin>
            <ymin>57.21</ymin>
            <xmax>201.82</xmax>
            <ymax>68.32</ymax>
        </bndbox>
    </object>
    <object>
        <name>1</name>
        <bndbox>
            <xmin>94.16</xmin>
            <ymin>166.63</ymin>
            <xmax>105.28</xmax>
            <ymax>177.74</ymax>
        </bndbox>
    </object>
</annotation>
