<?xml version="1.0"?>
<annotation>
    <filename>000003635.jpg</filename>
    <source>
        <annotation>ArcGIS Pro 2.1</annotation>
    </source>
    <size>
        <width>224</width>
        <height>224</height>
        <depth>3</depth>
    </size>
    <object>
        <name>1</name>
        <bndbox>
            <xmin>119.64</xmin>
            <ymin>3.00</ymin>
            <xmax>130.75</xmax>
            <ymax>14.12</ymax>
        </bndbox>
    </object>
    <object>
        <name>1</name>
        <bndbox>
            <xmin>99.89</xmin>
            <ymin>15.35</ymin>
            <xmax>111.01</xmax>
            <ymax>26.46</ymax>
        </bndbox>
    </object>
    <object>
        <name>1</name>
        <bndbox>
            <xmin>88.85</xmin>
            <ymin>22.85</ymin>
            <xmax>99.96</xmax>
            <ymax>33.96</ymax>
        </bndbox>
    </object>
    <object>
        <name>1</name>
        <bndbox>
            <xmin>79.11</xmin>
            <ymin>29.75</ymin>
            <xmax>90.22</xmax>
            <ymax>40.86</ymax>
        </bndbox>
    </object>
    <object>
        <name>1</name>
        <bndbox>
            <xmin>36.91</xmin>
            <ymin>56.43</ymin>
            <xmax>48.02</xmax>
            <ymax>67.54</ymax>
        </bndbox>
    </object>
    <object>
        <name>1</name>
        <bndbox>
            <xmin>27.06</xmin>
            <ymin>64.89</ymin>
            <xmax>38.17</xmax>
            <ymax>76.00</ymax>
        </bndbox>
    </object>
    <object>
        <name>1</name>
        <bndbox>
            <xmin>123.44</xmin>
            <ymin>97.35</ymin>
            <xmax>134.55</xmax>
            <ymax>108.46</ymax>
        </bndbox>
    </object>
    <object>
        <name>1</name>
        <bndbox>
            <xmin>148.92</xmin>
            <ymin>80.66</ymin>
            <xmax>160.03</xmax>
            <ymax>91.78</ymax>
        </bndbox>
    </object>
    <object>
        <name>1</name>
        <bndbox>
            <xmin>171.80</xmin>
            <ymin>65.35</ymin>
            <xmax>182.91</xmax>
            <ymax>76.46</ymax>
        </bndbox>
    </object>
    <object>
        <name>1</name>
        <bndbox>
            <xmin>203.31</xmin>
            <ymin>43.93</ymin>
            <xmax>214.42</xmax>
            <ymax>55.04</ymax>
        </bndbox>
    </object>
    <object>
        <name>1</name>
        <bndbox>
            <xmin>205.28</xmin>
            <ymin>97.65</ymin>
            <xmax>216.39</xmax>
            <ymax>108.76</ymax>
        </bndbox>
    </object>
    <object>
        <name>1</name>
        <bndbox>
            <xmin>176.01</xmin>
            <ymin>117.68</ymin>
            <xmax>187.12</xmax>
            <ymax>128.79</ymax>
        </bndbox>
    </object>
    <object>
        <name>1</name>
        <bndbox>
            <xmin>149.24</xmin>
            <ymin>134.51</ymin>
            <xmax>160.35</xmax>
            <ymax>145.62</ymax>
        </bndbox>
    </object>
    <object>
        <name>1</name>
        <bndbox>
            <xmin>59.29</xmin>
            <ymin>0.22</ymin>
            <xmax>70.41</xmax>
            <ymax>11.33</ymax>
        </bndbox>
    </object>
</annotation>
