<?xml version="1.0"?>
<annotation>
    <filename>000001035.jpg</filename>
    <source>
        <annotation>ArcGIS Pro 2.1</annotation>
    </source>
    <size>
        <width>224</width>
        <height>224</height>
        <depth>3</depth>
    </size>
    <object>
        <name>1</name>
        <bndbox>
            <xmin>8.31</xmin>
            <ymin>46.07</ymin>
            <xmax>19.42</xmax>
            <ymax>57.19</ymax>
        </bndbox>
    </object>
    <object>
        <name>1</name>
        <bndbox>
            <xmin>74.93</xmin>
            <ymin>0.96</ymin>
            <xmax>86.04</xmax>
            <ymax>12.08</ymax>
        </bndbox>
    </object>
    <object>
        <name>1</name>
        <bndbox>
            <xmin>53.57</xmin>
            <ymin>15.15</ymin>
            <xmax>64.68</xmax>
            <ymax>26.27</ymax>
        </bndbox>
    </object>
    <object>
        <name>1</name>
        <bndbox>
            <xmin>49.42</xmin>
            <ymin>106.37</ymin>
            <xmax>60.53</xmax>
            <ymax>117.49</ymax>
        </bndbox>
    </object>
    <object>
        <name>1</name>
        <bndbox>
            <xmin>59.96</xmin>
            <ymin>99.54</ymin>
            <xmax>71.07</xmax>
            <ymax>110.65</ymax>
        </bndbox>
    </object>
    <object>
        <name>1</name>
        <bndbox>
            <xmin>83.46</xmin>
            <ymin>84.44</ymin>
            <xmax>94.58</xmax>
            <ymax>95.55</ymax>
        </bndbox>
    </object>
    <object>
        <name>1</name>
        <bndbox>
            <xmin>94.58</xmin>
            <ymin>76.60</ymin>
            <xmax>105.69</xmax>
            <ymax>87.71</ymax>
        </bndbox>
    </object>
    <object>
        <name>1</name>
        <bndbox>
            <xmin>163.94</xmin>
            <ymin>28.93</ymin>
            <xmax>175.06</xmax>
            <ymax>40.04</ymax>
        </bndbox>
    </object>
</annotation>
