<?xml version="1.0"?>
<annotation>
    <filename>000002305.jpg</filename>
    <source>
        <annotation>ArcGIS Pro 2.1</annotation>
    </source>
    <size>
        <width>224</width>
        <height>224</height>
        <depth>3</depth>
    </size>
    <object>
        <name>1</name>
        <bndbox>
            <xmin>102.30</xmin>
            <ymin>177.19</ymin>
            <xmax>113.41</xmax>
            <ymax>188.30</ymax>
        </bndbox>
    </object>
    <object>
        <name>1</name>
        <bndbox>
            <xmin>184.65</xmin>
            <ymin>168.44</ymin>
            <xmax>195.76</xmax>
            <ymax>179.55</ymax>
        </bndbox>
    </object>
    <object>
        <name>1</name>
        <bndbox>
            <xmin>192.34</xmin>
            <ymin>179.56</ymin>
            <xmax>203.45</xmax>
            <ymax>190.67</ymax>
        </bndbox>
    </object>
</annotation>
