<?xml version="1.0"?>
<annotation>
    <filename>000002467.jpg</filename>
    <source>
        <annotation>ArcGIS Pro 2.1</annotation>
    </source>
    <size>
        <width>224</width>
        <height>224</height>
        <depth>3</depth>
    </size>
    <object>
        <name>2</name>
        <bndbox>
            <xmin>21.48</xmin>
            <ymin>0.00</ymin>
            <xmax>64.68</xmax>
            <ymax>17.01</ymax>
        </bndbox>
    </object>
    <object>
        <name>2</name>
        <bndbox>
            <xmin>93.72</xmin>
            <ymin>67.99</ymin>
            <xmax>138.17</xmax>
            <ymax>112.43</ymax>
        </bndbox>
    </object>
    <object>
        <name>2</name>
        <bndbox>
            <xmin>203.12</xmin>
            <ymin>220.66</ymin>
            <xmax>224.00</xmax>
            <ymax>224.00</ymax>
        </bndbox>
    </object>
</annotation>
