<?xml version="1.0"?>
<annotation>
    <filename>000002990.jpg</filename>
    <source>
        <annotation>ArcGIS Pro 2.1</annotation>
    </source>
    <size>
        <width>224</width>
        <height>224</height>
        <depth>3</depth>
    </size>
    <object>
        <name>2</name>
        <bndbox>
            <xmin>83.56</xmin>
            <ymin>20.35</ymin>
            <xmax>128.01</xmax>
            <ymax>64.79</ymax>
        </bndbox>
    </object>
    <object>
        <name>1</name>
        <bndbox>
            <xmin>19.62</xmin>
            <ymin>178.42</ymin>
            <xmax>30.73</xmax>
            <ymax>189.53</ymax>
        </bndbox>
    </object>
    <object>
        <name>1</name>
        <bndbox>
            <xmin>20.74</xmin>
            <ymin>168.67</ymin>
            <xmax>31.85</xmax>
            <ymax>179.78</ymax>
        </bndbox>
    </object>
</annotation>
