<?xml version="1.0"?>
<annotation>
    <filename>000001393.jpg</filename>
    <source>
        <annotation>ArcGIS Pro 2.1</annotation>
    </source>
    <size>
        <width>224</width>
        <height>224</height>
        <depth>3</depth>
    </size>
    <object>
        <name>2</name>
        <bndbox>
            <xmin>0.00</xmin>
            <ymin>213.74</ymin>
            <xmax>31.50</xmax>
            <ymax>224.00</ymax>
        </bndbox>
    </object>
    <object>
        <name>1</name>
        <bndbox>
            <xmin>158.53</xmin>
            <ymin>213.69</ymin>
            <xmax>169.64</xmax>
            <ymax>224.00</ymax>
        </bndbox>
    </object>
    <object>
        <name>1</name>
        <bndbox>
            <xmin>147.41</xmin>
            <ymin>199.42</ymin>
            <xmax>158.52</xmax>
            <ymax>210.54</ymax>
        </bndbox>
    </object>
    <object>
        <name>1</name>
        <bndbox>
            <xmin>216.40</xmin>
            <ymin>0.00</ymin>
            <xmax>224.00</xmax>
            <ymax>6.40</ymax>
        </bndbox>
    </object>
</annotation>
